torra/bencod.py
torra/confs.py
torra/conmenu.py
torra/cons.py
torra/gtk.py
torra/layout.py
torra/listtor.py
torra/log.py
torra/main.py
torra/meninfo.py
torra/next.py
torra/overall.py
torra/ratio.py
torra/sets.py
torra/stats.py
torra/torben.py
torra/torrent.py
torra/treesel.py
torra-1.0.40.dist-info/METADATA
torra-1.0.40.dist-info/WHEEL
torra-1.0.40.dist-info/entry_points.txt
torra-1.0.40.dist-info/top_level.txt
torra-1.0.40.dist-info/RECORD
