Metadata-Version: 2.1
Name: torra
Version: 1.0.40
Summary: Torrent client
Home-page: https://github.com/colin-i/tora
Author: cb
Author-email: costin.botescu@gmail.com
License: MIT
Requires-Python: >=3
Requires-Dist: appdirs >=1.4.3
Requires-Dist: libtorrent
